<chump>
	<!-- Car respawner -->
	<append xpath="/blockplaceholders">
		<placeholder name="lootCarRespawner">
			<block name="cntBarrelOilSingle00" />
			<block name="cntCar03SedanDamage0Master" />
			<block name="cntCar03SedanDamage1Master" />
			<block name="cntCar03SedanDamage2Master" />
			<block name="cntBusSchool" />
			<block name="cntBusSchoolShort" />
			<block name="cntBusShuttle" />
			<block name="cntBusCity" />
			<block name="cntArmyTruckOpen" />
			<block name="cntArmyTruckClosed" />
		</placeholder>
	</append>
</chump>